fstring427/__init__.py
fstring427/flogging.py
fstring427/fstring.py
fstring427-0.9.9.dist-info/DESCRIPTION.rst
fstring427-0.9.9.dist-info/METADATA
fstring427-0.9.9.dist-info/RECORD
fstring427-0.9.9.dist-info/WHEEL
fstring427-0.9.9.dist-info/metadata.json
fstring427-0.9.9.dist-info/top_level.txt
