Metadata-Version: 2.0
Name: fstring427
Version: 0.9.9
Summary: Python 3.6 f-string sympathy for  Python 2.7. Now with printf()
Home-page: https://github.com/smartvid-io/fstring427
Author: Sean True
Author-email: strue@smartvid.io
License: MIT
Keywords: programmer productivity
Platform: UNKNOWN
Classifier: Development Status :: 4 - Beta
Classifier: Intended Audience :: Developers
Classifier: Topic :: Software Development :: Build Tools
Classifier: License :: OSI Approved :: MIT License
Classifier: Programming Language :: Python :: 2.7
